measury/__init__.py
measury/__main__.py
measury/_version.py
measury/app.py
measury/data_handler.py
measury/drawable_objects.py
measury/main_ui.py
measury/main_window.py
measury/right_ui.py
measury/settings.py
measury/vispy_canvas.py
measury/windows.py
measury/data/gear_icon.png
measury/data/ghost_icon.png
measury/data/microscopes.py
measury/data/show_icon.png
measury/data/tape_measure_128.ico
measury-1.6.4.dist-info/licenses/LICENSE
measury-1.6.4.dist-info/METADATA
measury-1.6.4.dist-info/WHEEL
measury-1.6.4.dist-info/top_level.txt
measury-1.6.4.dist-info/RECORD
