Metadata-Version: 2.4
Name: measury
Version: 1.6.4
Summary: A tool to measure pictures with scale_bars
License: MIT License
Project-URL: repository, https://github.com/ullmannJan/measury
Classifier: Development Status :: 3 - Alpha
Classifier: Intended Audience :: Science/Research
Classifier: License :: OSI Approved :: MIT License
Classifier: Operating System :: OS Independent
Classifier: Programming Language :: Python :: 3
Classifier: Topic :: Scientific/Engineering :: Visualization
Classifier: Topic :: Utilities
Requires-Python: >=3.10
License-File: LICENSE
Requires-Dist: numpy
Requires-Dist: vispy>=0.14.3
Requires-Dist: PySide6
Requires-Dist: pyopengl
Requires-Dist: opencv-python
Requires-Dist: scipy
Requires-Dist: importlib-metadata
Provides-Extra: dev
Requires-Dist: pytest; extra == "dev"
Requires-Dist: pyinstaller; extra == "dev"
Dynamic: license-file
